vagrant/__init__.py
vagrant/_version.py
vagrant/compat.py
vagrant/py.typed
vagrant/test.py
vagpy-0.1.dev1.dist-info/LICENSE.txt
vagpy-0.1.dev1.dist-info/METADATA
vagpy-0.1.dev1.dist-info/WHEEL
vagpy-0.1.dev1.dist-info/top_level.txt
vagpy-0.1.dev1.dist-info/RECORD
