Metadata-Version: 2.1
Name: vagpy
Version: 0.1.dev1
Summary: Python bindings for interacting with Vagrant virtual machines.
Author-email: Todd Francis DeLuca <todddeluca@yahoo.com>
Maintainer-email: Sorin Sbarnea <sorin.sbarnea@gmail.com>
License: MIT
Project-URL: homepage, https://github.com/pycontribs/python-vagrant
Project-URL: repository, https://github.com/pycontribs/python-vagrant
Project-URL: changelog, https://github.com/pycontribs/python-vagrant/releases
Keywords: box,vagrant,vagrantfile,virtual-machine,virtualbox
Classifier: Development Status :: 4 - Beta
Classifier: License :: OSI Approved :: MIT License
Classifier: Operating System :: OS Independent
Classifier: Programming Language :: Python :: 3.9
Classifier: Programming Language :: Python :: 3.10
Classifier: Programming Language :: Python :: 3.11
Classifier: Topic :: Utilities
Requires-Python: >=3.9
License-File: LICENSE.txt
Provides-Extra: test
Requires-Dist: coverage[toml] >=7.0.3 ; extra == 'test'
Requires-Dist: pytest >=7.2.0 ; extra == 'test'
Requires-Dist: pytest-plus >=0.4.0 ; extra == 'test'
Requires-Dist: pytest-github-actions-annotate-failures >=0.1.8 ; extra == 'test'
